rabbitmonitor/__init__.py
rabbitmonitor/__main__.py
rabbitmonitor-2.0.0.dist-info/LICENSE
rabbitmonitor-2.0.0.dist-info/METADATA
rabbitmonitor-2.0.0.dist-info/WHEEL
rabbitmonitor-2.0.0.dist-info/entry_points.txt
rabbitmonitor-2.0.0.dist-info/top_level.txt
rabbitmonitor-2.0.0.dist-info/RECORD
