Metadata-Version: 2.1
Name: rabbitmonitor
Version: 2.0.0
Summary: A simple server monitor
Home-page: https://github.com/Rabbit-Company/RabbitMonitor
Author: Rabbit Company LLC
Author-email: info@rabbit-company.com
License: GPLv3
Project-URL: Bug Tracker, https://github.com/Rabbit-Company/RabbitMonitor/issues
Keywords: rabbit,monitor
Classifier: Programming Language :: Python :: 3
Classifier: License :: OSI Approved :: GNU General Public License v3 (GPLv3)
Classifier: Operating System :: OS Independent
Requires-Python: >=3.8
License-File: LICENSE
Requires-Dist: quart (>=0.17.0)
Requires-Dist: psutil (>=5.9.0)
Requires-Dist: argparse (>=1.4.0)
